{
  "annotations": {
    "list": [
      {
        "builtIn": 1,
        "datasource": "-- Grafana --",
        "enable": true,
        "hide": true,
        "iconColor": "rgba(0, 211, 255, 1)",
        "name": "Annotations & Alerts",
        "type": "dashboard"
      }
    ]
  },
  "editable": true,
  "gnetId": null,
  "graphTooltip": 0,
  "id": null,
  "links": [],
  "panels": [
    {
      "datasource": "Prometheus",
      "fieldConfig": {
        "defaults": {
          "color": {
            "mode": "palette-classic"
          },
          "custom": {
            "axisLabel": "",
            "axisPlacement": "auto",
            "barAlignment": 0,
            "drawStyle": "line",
            "fillOpacity": 10,
            "gradientMode": "none",
            "hideFrom": {
              "tooltip": false,
              "viz": false,
              "legend": false
            },
            "lineInterpolation": "linear",
            "lineWidth": 2,
            "pointSize": 5,
            "scaleDistribution": {
              "type": "linear"
            },
            "showPoints": "auto",
            "spanNulls": false,
            "stacking": {
              "group": "A",
              "mode": "none"
            },
            "thresholdsStyle": {
              "mode": "off"
            }
          },
          "mappings": [],
          "max": 1,
          "min": 0,
          "thresholds": {
            "mode": "absolute",
            "steps": [
              {
                "color": "green",
                "value": null
              }
            ]
          },
          "unit": "percentunit"
        }
      },
      "gridPos": {
        "h": 10,
        "w": 24,
        "x": 0,
        "y": 0
      },
      "id": 1,
      "options": {
        "legend": {
          "calcs": ["last", "mean"],
          "displayMode": "table",
          "placement": "right"
        },
        "tooltip": {
          "mode": "multi"
        }
      },
      "pluginVersion": "8.0.0",
      "targets": [
        {
          "expr": "keycloak_migration_progress",
          "legendFormat": "{{tenant}}{{node}} - {{from_version}} → {{to_version}}",
          "refId": "A"
        }
      ],
      "title": "Migration Progress - All Instances",
      "type": "timeseries"
    },
    {
      "datasource": "Prometheus",
      "fieldConfig": {
        "defaults": {
          "color": {
            "mode": "thresholds"
          },
          "mappings": [],
          "max": 1,
          "min": 0,
          "thresholds": {
            "mode": "absolute",
            "steps": [
              {
                "color": "red",
                "value": null
              },
              {
                "color": "yellow",
                "value": 0.3
              },
              {
                "color": "green",
                "value": 0.7
              }
            ]
          },
          "unit": "percentunit"
        }
      },
      "gridPos": {
        "h": 12,
        "w": 24,
        "x": 0,
        "y": 10
      },
      "id": 2,
      "options": {
        "orientation": "horizontal",
        "reduceOptions": {
          "calcs": ["lastNotNull"],
          "fields": "",
          "values": false
        },
        "showThresholdLabels": false,
        "showThresholdMarkers": true,
        "text": {}
      },
      "pluginVersion": "8.0.0",
      "targets": [
        {
          "expr": "keycloak_migration_progress",
          "legendFormat": "{{tenant}}{{node}}",
          "refId": "A"
        }
      ],
      "title": "Per-Instance Progress (Gauges)",
      "type": "gauge",
      "transformations": [
        {
          "id": "seriesToRows",
          "options": {}
        }
      ]
    },
    {
      "datasource": "Prometheus",
      "fieldConfig": {
        "defaults": {
          "color": {
            "mode": "thresholds"
          },
          "custom": {
            "align": "auto",
            "displayMode": "auto"
          },
          "mappings": [
            {
              "options": {
                "0": {
                  "color": "text",
                  "index": 0,
                  "text": "⏳ Pending"
                },
                "1": {
                  "color": "blue",
                  "index": 1,
                  "text": "🔄 In Progress"
                },
                "2": {
                  "color": "green",
                  "index": 2,
                  "text": "✅ Completed"
                },
                "3": {
                  "color": "red",
                  "index": 3,
                  "text": "❌ Failed"
                }
              },
              "type": "value"
            }
          ],
          "thresholds": {
            "mode": "absolute",
            "steps": [
              {
                "color": "green",
                "value": null
              }
            ]
          }
        },
        "overrides": [
          {
            "matcher": {
              "id": "byName",
              "options": "checkpoint"
            },
            "properties": [
              {
                "id": "custom.width",
                "value": 150
              }
            ]
          }
        ]
      },
      "gridPos": {
        "h": 10,
        "w": 24,
        "x": 0,
        "y": 22
      },
      "id": 3,
      "options": {
        "showHeader": true,
        "sortBy": []
      },
      "pluginVersion": "8.0.0",
      "targets": [
        {
          "expr": "keycloak_migration_checkpoint_status",
          "format": "table",
          "instant": true,
          "refId": "A"
        }
      ],
      "title": "Checkpoint Status - All Instances",
      "transformations": [
        {
          "id": "organize",
          "options": {
            "excludeByName": {
              "Time": true,
              "__name__": true
            },
            "indexByName": {},
            "renameByName": {
              "Value": "Status",
              "checkpoint": "Checkpoint",
              "tenant": "Tenant",
              "node": "Node"
            }
          }
        }
      ],
      "type": "table"
    },
    {
      "datasource": "Prometheus",
      "fieldConfig": {
        "defaults": {
          "color": {
            "mode": "palette-classic"
          },
          "custom": {
            "axisLabel": "",
            "axisPlacement": "auto",
            "barAlignment": 0,
            "drawStyle": "bars",
            "fillOpacity": 100,
            "gradientMode": "none",
            "hideFrom": {
              "tooltip": false,
              "viz": false,
              "legend": false
            },
            "lineInterpolation": "linear",
            "lineWidth": 1,
            "pointSize": 5,
            "scaleDistribution": {
              "type": "linear"
            },
            "showPoints": "auto",
            "spanNulls": false,
            "stacking": {
              "group": "A",
              "mode": "normal"
            },
            "thresholdsStyle": {
              "mode": "off"
            }
          },
          "mappings": [],
          "thresholds": {
            "mode": "absolute",
            "steps": [
              {
                "color": "green",
                "value": null
              }
            ]
          }
        }
      },
      "gridPos": {
        "h": 8,
        "w": 12,
        "x": 0,
        "y": 32
      },
      "id": 4,
      "options": {
        "legend": {
          "calcs": [],
          "displayMode": "list",
          "placement": "bottom"
        },
        "tooltip": {
          "mode": "multi"
        }
      },
      "targets": [
        {
          "expr": "rate(keycloak_migration_errors_total[5m])",
          "legendFormat": "{{tenant}}{{node}} - {{error_type}}",
          "refId": "A"
        }
      ],
      "title": "Error Rate by Instance",
      "type": "timeseries"
    },
    {
      "datasource": "Prometheus",
      "fieldConfig": {
        "defaults": {
          "color": {
            "mode": "thresholds"
          },
          "mappings": [],
          "thresholds": {
            "mode": "absolute",
            "steps": [
              {
                "color": "green",
                "value": null
              },
              {
                "color": "red",
                "value": 5
              }
            ]
          }
        }
      },
      "gridPos": {
        "h": 8,
        "w": 12,
        "x": 12,
        "y": 32
      },
      "id": 5,
      "options": {
        "colorMode": "value",
        "graphMode": "area",
        "justifyMode": "auto",
        "orientation": "auto",
        "reduceOptions": {
          "calcs": ["sum"],
          "fields": "",
          "values": false
        },
        "text": {},
        "textMode": "auto"
      },
      "pluginVersion": "8.0.0",
      "targets": [
        {
          "expr": "sum by (tenant, node) (keycloak_migration_errors_total)",
          "legendFormat": "{{tenant}}{{node}}",
          "refId": "A"
        }
      ],
      "title": "Total Errors per Instance",
      "type": "stat"
    }
  ],
  "refresh": "5s",
  "schemaVersion": 27,
  "style": "dark",
  "tags": ["keycloak", "migration", "multi-instance"],
  "templating": {
    "list": [
      {
        "allValue": null,
        "current": {
          "selected": true,
          "text": "All",
          "value": "$__all"
        },
        "datasource": "Prometheus",
        "definition": "label_values(keycloak_migration_progress, tenant)",
        "hide": 0,
        "includeAll": true,
        "label": "Tenant",
        "multi": true,
        "name": "tenant",
        "options": [],
        "query": {
          "query": "label_values(keycloak_migration_progress, tenant)",
          "refId": "StandardVariableQuery"
        },
        "refresh": 1,
        "regex": "",
        "skipUrlSync": false,
        "sort": 0,
        "type": "query"
      },
      {
        "allValue": null,
        "current": {
          "selected": true,
          "text": "All",
          "value": "$__all"
        },
        "datasource": "Prometheus",
        "definition": "label_values(keycloak_migration_progress, node)",
        "hide": 0,
        "includeAll": true,
        "label": "Node",
        "multi": true,
        "name": "node",
        "options": [],
        "query": {
          "query": "label_values(keycloak_migration_progress, node)",
          "refId": "StandardVariableQuery"
        },
        "refresh": 1,
        "regex": "",
        "skipUrlSync": false,
        "sort": 0,
        "type": "query"
      }
    ]
  },
  "time": {
    "from": "now-30m",
    "to": "now"
  },
  "timepicker": {},
  "timezone": "",
  "title": "Keycloak Migration - Multi-Instance Dashboard",
  "uid": "keycloak-migration-multi",
  "version": 1
}
